{
  "login_title": "Inicia sesión en tu cuenta",
  "login_subtitle": "Ingresa tu correo electrónico y contraseña",
  "email": "Correo electrónico",
  "password": "Contraseña",
  "forgot_password": "¿Olvidaste tu contraseña?",
  "forgot_password_title": "Olvidé mi contraseña",
  "forgot_password_subtitle": "Ingresa tu correo para recibir un código OTP",
  "send_verification_code": "Enviar código de verificación",
  "otp_verification_title": "Verificación OTP",
  "otp_instruction_prefix": "Ingresa el código de 6 dígitos enviado a tu correo: ",
  "otp_invalid_length": "Ingresa el código OTP de 6 dígitos",
  "otp_not_received": "¿No recibiste el código?",
  "otp_resend_code": "Reenviar código",
  "verify": "Verificar",
  "login": "Iniciar sesión",
  "or": "O",
  "create_account": "Crear cuenta",
  "terms_login_prefix": "Al iniciar sesión, aceptas ",
  "terms_and_conditions": "Términos y condiciones",
  "and": " y ",
  "privacy_policy": "Política de privacidad",

  "register_title": "Crear cuenta",
  "name": "Nombre",
  "training_program": "Programa de capacitación",
  "batch": "Grupo",
  "gender": "Género",
  "loading_data": "Cargando datos...",
  "load_data_failed_retry": "Error al cargar datos. Inténtalo de nuevo.",
  "reload": "Recargar",
  "gender_load_failed": "Error al cargar datos de género.",
  "gender_unavailable": "Datos de género no disponibles",
  "training_unavailable": "Datos de capacitación no disponibles",
  "batch_unavailable": "Datos de grupo no disponibles",
  "continue": "Continuar",
  "gender_required": "El género es obligatorio",
  "required_select_template": "{field} es obligatorio",
  "step_create_account": "Cuenta",
  "step_password": "Contraseña",
  "step_profile_photo": "Foto",
  "step_success": "Éxito",

  "password_page_title": "Contraseña",
  "password_page_subtitle": "Crea una contraseña para tu cuenta",
  "create_password": "Crear contraseña",
  "confirm_password": "Confirmar contraseña",
  "password_confirm_mismatch": "La confirmación de contraseña no coincide",
  "reset_password_title": "Crear nueva contraseña",
  "reset_password_subtitle": "Elige una que sea fácil de recordar",
  "reset_password_success_login": "Contraseña cambiada exitosamente. Por favor inicia sesión nuevamente.",
  "reset_password_button": "Cambiar contraseña",
  "new_password_label": "Nueva contraseña",
  "password_changed_success": "Contraseña cambiada exitosamente",

  "photo_page_title": "Establecer foto de perfil",
  "choose_photo_source": "Elegir fuente de foto",
  "camera": "Cámara",
  "gallery": "Galería",
  "take_from_camera": "Tomar desde cámara",
  "pick_from_gallery": "Elegir de galería",
  "photo_pick_failed": "Error al seleccionar foto",
  "photo_required_register": "Se requiere foto de perfil antes de crear cuenta",
  "create_account_button": "Crear cuenta",

  "welcome_workfra": "Bienvenido a\nWorkfra",
  "success_account_created": "Tu cuenta ha sido creada.\nLa asistencia ahora es más fácil para ti",

  "validation_email_required": "El correo es obligatorio",
  "validation_email_invalid": "Formato de correo inválido",
  "validation_password_required": "La contraseña es obligatoria",
  "validation_password_min": "La contraseña debe tener al menos 6 caracteres",
  "validation_name_required": "El nombre es obligatorio",
  "validation_name_min": "El nombre debe tener al menos 2 caracteres",

  "app_exit_hint": "Presiona de nuevo para salir de la aplicación",
  "user_default_name": "Usuario",
  "latest_history": "Historial reciente",
  "see_all": "Ver todo",
  "no_history_attendance_leave": "Aún no hay historial de asistencia o permisos",

  "greeting_morning": "Buenos días",
  "greeting_afternoon": "Buenas tardes",
  "greeting_evening": "Buenas tardes",
  "greeting_night": "Buenas noches",

  "nav_home": "Inicio",
  "nav_history": "Historial",
  "nav_leave": "Permiso",
  "nav_statistics": "Estadísticas",

  "status_late": "Tarde",
  "status_absent": "Ausente",
  "status_present": "Presente",
  "status_leave": "Permiso",
  "status_unknown": "-",
  "status_done": "Completado",
  "status_active": "Activo",
  "status_not_checked_in": "Sin registro",
  "check_in": "Entrada",
  "check_out": "Salida",
  "enter": "Entrada",
  "leave": "Salida",
  "check_in_upper": "ENTRADA",
  "check_out_upper": "SALIDA",
  "attendance_time_format": "{enter}: {in} • {leave}: {out}",
  "absent_without_note": "Sin descripción",
  "timezone_wib": "WIB",
  "attendance_today_title": "Asistencia de hoy, {name}",
  "attendance_check_times": "Entrada: {checkIn}  •  Salida: {checkOut}",
  "attendance_coordinates": "Lat {lat}, Lng {lng}",
  "attendance_coordinates_unavailable": "Coordenadas de ubicación aún no disponibles",
  "attendance_radius_area_label": "Área de asistencia en radio de 500m desde PPKD Jakarta Pusat",
  "attendance_outside_area": "Estás fuera del área de asistencia (500m)",
  "attendance_fetching_location": "Obteniendo ubicación precisa... asegúrate de que el GPS esté activado",
  "attendance_radius_hint": "Radio de asistencia de 500m desde PPKD Jakarta Pusat. Asegúrate de que el GPS esté activado y la ubicación sea estable antes del registro.",
  "attendance_rejected_title": "Asistencia rechazada",
  "attendance_check_in_success": "¡Entrada exitosa!",
  "attendance_check_out_success": "¡Salida exitosa!",
  "attendance_action_failed": "Error al procesar la asistencia.",
  "loading_location": "Cargando ubicación...",
  "location_fetch_failed": "Error al obtener ubicación",
  "address_not_found": "Dirección no encontrada",
  "address_fetch_failed": "Error al obtener dirección",

  "history_screen_title": "Historial de asistencia y permisos",
  "filter": "Filtrar",
  "reset": "Restablecer",
  "delete_history_title": "¿Eliminar historial?",
  "delete_history_message": "Los datos de asistencia se eliminarán permanentemente",
  "enter_password": "Ingresa la contraseña",
  "cancel": "Cancelar",
  "password_wrong": "Contraseña incorrecta",
  "delete": "Eliminar",
  "delete_failed": "Error al eliminar datos",
  "date_range_help": "Seleccionar rango de fechas",
  "apply": "Aplicar",
  "no_history_selected_range": "No hay historial en el rango seleccionado",
  "retry": "Reintentar",

  "leave_title": "Solicitud de permiso",
  "pick_date": "Seleccionar fecha",
  "date_placeholder": "mm/dd/aaaa",
  "leave_type": "Tipo de permiso",
  "select_category": "Seleccionar categoría...",
  "leave_type_required": "Selecciona el tipo de permiso",
  "leave_reason_label": "Escribe el motivo del permiso...",
  "leave_reason_hint": "Describe el motivo de tu permiso...",
  "leave_reason_required": "El motivo es obligatorio",
  "submit_leave": "Enviar permiso",
  "leave_submitted_success": "Permiso enviado exitosamente",
  "your_leave_history": "Tu historial de permisos",
  "no_history_yet": "Aún no hay historial",
  "select_date_first": "Selecciona una fecha primero",

  "leave_type_sick": "Enfermedad",
  "leave_type_permission": "Permiso",
  "leave_type_other": "Otro",
  "processed_at": "Procesado: {datetime}",
  "status_approved": "Aprobado",
  "status_pending": "Pendiente",
  "status_rejected": "Rechazado",

  "requirement_title": "Activar funciones requeridas",
  "requirement_both": "Wi-Fi o datos móviles y GPS deben estar activados para el correcto funcionamiento.",
  "requirement_internet": "Wi-Fi o datos móviles deben estar activados para usar las funciones.",
  "requirement_gps": "El GPS debe estar activado para usar las funciones.",

  "statistics": "Estadísticas",
  "summary_this_month": "Resumen del mes",
  "workdays": "Días laborales",
  "attendance_insight": "Análisis de asistencia",
  "avg_check_in": "Promedio\nEntrada",
  "avg_check_out": "Promedio\nSalida",
  "fastest_in": "Entrada\nmás rápida",
  "latest_out": "Salida\nmás tarde",
  "on_time_percentage": "Porcentaje de puntualidad",
  "on_time_subtitle_90": "¡Eres muy disciplinado este mes!",
  "on_time_subtitle_75": "Tu asistencia es bastante buena.",
  "on_time_subtitle_50": "Aún hay margen de mejora.",
  "on_time_subtitle_default": "¡Mejoremos tu asistencia!",
  "fun_fact": "DATO CURIOSO",
  "stats_fun_fact_no_data": "Aún no hay datos de asistencia para analizar.",
  "stats_fun_fact_leave_only": "Los datos actuales son solo permisos y no cuentan como días laborales.",
  "stats_fun_fact_early_day": "Sueles registrarte más temprano los {day}. ¡Gran consistencia!",
  "stats_fun_fact_min_attendance_hint": "Los datos curiosos están disponibles después de al menos {required} días. Aún necesitas {remaining} día(s) más.",
  "stats_fun_fact_best_day": "¡{day} es tu día con mayor asistencia!",
  "stats_fun_fact_keep_up": "¡Sigue manteniendo tu asistencia para mejores análisis!",

  "profile_choose_photo_source": "Elegir fuente de foto",
  "take_photo_direct": "Tomar foto directamente",
  "choose_photo_gallery": "Elegir foto de galería",
  "profile_photo_updated": "Foto de perfil actualizada exitosamente",
  "profile_photo_upload_failed": "Error al subir foto",
  "logout_title": "Cerrar sesión",
  "logout_message": "¿Estás seguro de que quieres cerrar sesión?",
  "logout": "Cerrar sesión",
  "profile_not_available": "Datos de perfil no disponibles.",
  "personal_info": "Información personal",
  "edit": "EDITAR",
  "full_name_upper": "NOMBRE COMPLETO",
  "email_upper": "CORREO",
  "security": "Seguridad",
  "change_password": "Cambiar contraseña",
  "change_password_sending_subtitle": "Enviando código de verificación a tu correo...",
  "change_password_sending_otp": "Enviando código OTP...",
  "user_email_not_available": "Correo no disponible. Inicia sesión nuevamente.",
  "send_otp_failed": "Error al enviar OTP",
  "appearance": "Apariencia",
  "dark_mode": "Modo oscuro",
  "dark_mode_subtitle": "Usa el tema oscuro para mayor comodidad visual",
  "about_app": "Acerca de la app",
  "app_version": "Versión 1.0.0",
  "app_description": "Sistema inteligente de asistencia para gestión de horarios, solicitudes de permisos y monitoreo eficiente del historial.",
  "edit_profile_title": "Editar perfil",
  "edit_profile_subtitle": "Actualiza tu información personal",
  "full_name": "Nombre completo",
  "save_changes": "Guardar cambios",
  "profile_updated_success": "Perfil actualizado exitosamente",
  "close": "Cerrar",

  "error_session_expired": "Sesión expirada. Inicia sesión nuevamente.",
  "error_load_attendance_status": "Error al cargar estado de asistencia.",
  "error_check_in_failed": "Error al registrar entrada.",
  "error_check_out_failed": "Error al registrar salida.",
  "error_wifi_data_required": "Se requiere Wi-Fi o datos móviles para la asistencia.",
  "error_gps_required": "Se requiere GPS para la asistencia.",
  "error_location_permission_denied": "Permiso de ubicación no concedido.",
  "error_location_not_ready": "Ubicación no disponible. Asegúrate de que el GPS esté activado.",
  "error_mock_gps_detected": "GPS falso detectado. Desactívalo para continuar.",
  "error_invalid_attendance_date": "Fecha de asistencia inválida.",
  "error_location_unavailable": "Ubicación no disponible",
  "error_submit_leave": "Error al enviar solicitud de permiso.",
  "error_load_profile": "Error al cargar perfil.",
  "error_update_profile": "Error al actualizar perfil.",
  "error_upload_avatar": "Error al subir foto.",
  "error_load_history": "Error al cargar historial.",
  "error_delete_attendance": "Error al eliminar datos de asistencia.",
  "error_load_statistics": "Error al cargar estadísticas.",
  "error_network_unreachable": "Sin conexión a internet.",
  "error_request_timeout": "El servidor tarda demasiado en responder.",
  "error_server_unavailable": "Error del servidor. Inténtalo más tarde.",
  "error_connection_lost": "Conexión interrumpida. Inténtalo de nuevo.",
  "requirement_reload_failed": "Funciones requeridas no activas. Activa GPS, Wi-Fi o datos móviles.",
  "error_generic": "Ocurrió un error. Inténtalo de nuevo.",
  "error_session_after_register": "Sesión no disponible después del registro. Inténtalo de nuevo.",
  "error_load_training": "Error al cargar datos de capacitación.",
  "error_load_leave_history": "Error al cargar historial de permisos.",
  "leave_queued_offline": "Problema de red detectado. Tu solicitud fue guardada y se reintentará automáticamente.",
  "language": "Idioma",
  "language_subtitle": "Elige el idioma de la aplicación",
  "notification_title": "Notificaciones",
  "notification_empty": "Aún no hay notificaciones",
  "notification_today": "Hoy",
  "notification_this_week": "Esta semana",
  "error_outside_radius": "Estás fuera del área de asistencia (500m de PPKD Jakarta Pusat). Regresa al área para continuar.",
  "error_server": "Error en el servidor",
  "error_validation_failed": "Validación fallida",
  "error_upload_photo": "Error al subir foto",
  "unknown_error": "Ocurrió un error desconocido"
}
